blair_nn/__init__.py
blair_nn-0.1.dist-info/DESCRIPTION.rst
blair_nn-0.1.dist-info/METADATA
blair_nn-0.1.dist-info/RECORD
blair_nn-0.1.dist-info/WHEEL
blair_nn-0.1.dist-info/metadata.json
blair_nn-0.1.dist-info/top_level.txt
