Metadata-Version: 2.0
Name: blair-nn
Version: 0.1
Summary: Simple feed forward Neural Network
Home-page: UNKNOWN
Author: James Blair
Author-email: james.blair09@gmail.com
License: MIT
Platform: UNKNOWN
Classifier: Development Status :: 3 - Alpha
Classifier: License :: OSI Approved :: MIT License
Classifier: Programming Language :: Python :: 3.5
Requires-Dist: matplotlib
Requires-Dist: numpy
Requires-Dist: pandas
